vcdextension/__init__.py
vcdextension/entities/__init__.py
vcdextension/entities/entity.py
vcdextension/entities/network.py
vcdextension/entities/snapshot.py
vcdextension/entities/tenant.py
vcdextension/entities/virtualapp.py
vcdextension/entities/virtualdatacenter.py
vcdextension/entities/virtualmachine.py
vcdextension/libraries/__init__.py
vcdextension/libraries/constants.py
vcdextension/libraries/exceptions.py
vcdextension/libraries/logger.py
vcdextension/libraries/rabbitmqclient.py
vcdextension/libraries/serverutils.py
vcdextension/libraries/taskplanner.py
vcdextension/libraries/taskscheduler.py
vcdextension/libraries/vcloudsecurity.py
vcdextension/logic/__init__.py
vcdextension/logic/logicorgs.py
vcdextension/logic/logictasks.py
vcdextension/logic/logicvapps.py
vcdextension/logic/logicvms.py
vcdextension/persistence/__init__.py
vcdextension/persistence/persistence.py
vcdextension/services/__init__.py
vcdextension/services/servicerabbitmq.py
vcdextension/services/services.py
vcd_extension-0.0.2.dist-info/AUTHORS
vcd_extension-0.0.2.dist-info/LICENSE
vcd_extension-0.0.2.dist-info/METADATA
vcd_extension-0.0.2.dist-info/WHEEL
vcd_extension-0.0.2.dist-info/top_level.txt
vcd_extension-0.0.2.dist-info/RECORD
