Metadata-Version: 2.1
Name: vcd-extension
Version: 0.0.2
Summary: Extensibility for cloud management tools
Home-page: https://gitlab.fing.edu.uy/proyecto-grado-vcloud/vcd-extension-backend
Author: Marcelo Sureda
Author-email: msureda@gmail.com
License: Apache-2.0
Platform: UNKNOWN
Classifier: Environment :: Console
Classifier: Intended Audience :: Developers
Classifier: Intended Audience :: System Administrators
Classifier: License :: OSI Approved :: Apache Software License
Classifier: Operating System :: POSIX :: Linux
Classifier: Programming Language :: Python
Classifier: Programming Language :: Python :: 3
Classifier: Topic :: Software Development :: Libraries
Requires-Python: >=3.6
License-File: LICENSE
License-File: AUTHORS
Requires-Dist: APScheduler (>=3.7.0)
Requires-Dist: certifi (>=2020.12.5)
Requires-Dist: chardet (>=4.0.0)
Requires-Dist: humanfriendly (>=9.1)
Requires-Dist: idna (<3,>=2.5)
Requires-Dist: importlib-metadata (>=3.4.0)
Requires-Dist: lxml (>=4.6.2)
Requires-Dist: pep517 (>=0.9.1)
Requires-Dist: pickleDB (>=0.9.2)
Requires-Dist: pika (>=1.2.0)
Requires-Dist: pkg-resources (>=0.0.0)
Requires-Dist: Pygments (>=2.8.1)
Requires-Dist: python-dateutil (>=2.8.1)
Requires-Dist: pytz (>=2021.1)
Requires-Dist: pyvcloud (>=23.0.0)
Requires-Dist: PyYAML (>=5.4.1)
Requires-Dist: redis (>=3.5.3)
Requires-Dist: requests (==2.25.1)
Requires-Dist: six (>=1.15.0)
Requires-Dist: toml (>=0.10.2)
Requires-Dist: typing-extensions (>=3.7.4.3)
Requires-Dist: unittest-xml-reporting (>=3.0.4)
Requires-Dist: urllib3 (>=1.26.3)
Requires-Dist: vcd-api-schemas-type (>=9.1.2.dev10)
Requires-Dist: zipp (>=3.4.0)
